mikroj/__init__.py
mikroj/actors/__init__.py
mikroj/actors/base.py
mikroj/assets/logo.ico
mikroj/env.py
mikroj/errors.py
mikroj/macro_helper.py
mikroj/macros/analyze-particles.ijm
mikroj/macros/auto_threshold.ijm
mikroj/macros/mark_rois.ijm
mikroj/macros/show_image.ijm
mikroj/macros/z-color-code.ijm
mikroj/main.py
mikroj/registries/__init__.py
mikroj/registries/base.py
mikroj/registries/macro.py
mikroj/registries/utils.py
mikroj-0.1.20.dist-info/METADATA
mikroj-0.1.20.dist-info/WHEEL
mikroj-0.1.20.dist-info/entry_points.txt
mikroj-0.1.20.dist-info/RECORD
