Metadata-Version: 2.1
Name: mikroj
Version: 0.1.20
Summary: 
License: CC BY-NC 3.0
Author: jhnnsrs
Author-email: jhnnsrs@gmail.com
Requires-Python: >=3.8,<3.12
Classifier: License :: Other/Proprietary License
Classifier: Programming Language :: Python :: 3
Classifier: Programming Language :: Python :: 3.8
Classifier: Programming Language :: Python :: 3.9
Classifier: Programming Language :: Python :: 3.10
Classifier: Programming Language :: Python :: 3.11
Requires-Dist: arkitekt (>=0.4.45)
Requires-Dist: pyimagej (==1.4.0)
Requires-Dist: qtpy (>=2.3.0,<3.0.0)
Requires-Dist: scyjava (>=1.6.0,<2.0.0)
